awslabs/__init__.py
awslabs/prometheus_mcp_server/__init__.py
awslabs/prometheus_mcp_server/consts.py
awslabs/prometheus_mcp_server/models.py
awslabs/prometheus_mcp_server/server.py
awslabs_prometheus_mcp_server-0.2.10.dist-info/METADATA
awslabs_prometheus_mcp_server-0.2.10.dist-info/WHEEL
awslabs_prometheus_mcp_server-0.2.10.dist-info/entry_points.txt
awslabs_prometheus_mcp_server-0.2.10.dist-info/licenses/LICENSE
awslabs_prometheus_mcp_server-0.2.10.dist-info/licenses/NOTICE
awslabs_prometheus_mcp_server-0.2.10.dist-info/RECORD
